pyrosenium/__init__.py
pyrosenium/rosenium/__init__.py
pyrosenium/rosenium/core/__init__.py
pyrosenium/rosenium/core/_rosenium_abbrev_mapper.py
pyrosenium/rosenium/core/_rosenium_methods.py
pyrosenium/rosenium/core/rosenium_driver.py
pyrosenium/rosenium/helpers/__init__.py
pyrosenium/rosenium/helpers/base_driver.py
pyrosenium/rosepom/__init__.py
pyrosenium/rosepom/core/__init__.py
pyrosenium/rosepom/core/rosepom.py
pyrosenium/rosepom/core/rosepom_app.py
pyrosenium/rosepom/core/template/__init__.py
pyrosenium/rosepom/core/template/actions.py
pyrosenium/rosepom/core/template/data.py
pyrosenium/rosepom/core/template/items.py
pyrosenium/rosepom/core/template/page.py
pyrosenium/rosepom/helpers/__init__.py
pyrosenium/rosepom/helpers/rosenium_find_elements_methods.py
tests/__init__.py
tests/testenv_configs.py
tests/rosenium/__init__.py
tests/rosenium/core/__init__.py
tests/rosenium/core/rosenium_driver_test.py
tests/rosenium/core/rosenium_methods_test.py
tests/rosenium/helpers/__init__.py
tests/rosenium/helpers/base_driver_test.py
tests/rosepom/__init__.py
tests/rosepom/core/__init__.py
tests/rosepom/core/rosepom_page_test.py
tests/rosepom/core/template/__init__.py
tests/rosepom/core/template/actions.py
tests/rosepom/core/template/data.py
tests/rosepom/core/template/items.py
tests/rosepom/core/template/page.py
pyrosenium-0.1.2.dist-info/LICENSE
pyrosenium-0.1.2.dist-info/METADATA
pyrosenium-0.1.2.dist-info/WHEEL
pyrosenium-0.1.2.dist-info/entry_points.txt
pyrosenium-0.1.2.dist-info/top_level.txt
pyrosenium-0.1.2.dist-info/RECORD
